pyxzones/__main__.py
pyxzones/config.py
pyxzones/process.py
pyxzones/service.py
pyxzones/settings.py
pyxzones/snap.py
pyxzones/types.py
pyxzones/xewmh.py
pyxzones/xq.py
pyxzones/zone_display.py
pyxzones/zone_profile.py
pyxzones-0.0.1.dist-info/LICENSE.txt
pyxzones-0.0.1.dist-info/METADATA
pyxzones-0.0.1.dist-info/WHEEL
pyxzones-0.0.1.dist-info/entry_points.txt
pyxzones-0.0.1.dist-info/top_level.txt
pyxzones-0.0.1.dist-info/RECORD
