Metadata-Version: 2.1
Name: pyxzones
Version: 0.0.1
Summary: A Linux window management tool inspired by Microsoft's FancyZones
Author-email: Josh Gentry <jg@noclip.dev>
Project-URL: Homepage, https://github.com/joshgentry/pyxzones
Project-URL: Issues, https://github.com/joshgentry/pyxzones/issues
Keywords: pyx,zones,fancyzones
Classifier: Operating System :: POSIX :: Linux
Classifier: Programming Language :: Python :: 3
Classifier: Topic :: Software Development :: Libraries :: Python Modules
Requires-Python: >=3.10
License-File: LICENSE.txt
